{
  "beau_age_4": [
    {
      "set": 0,
      "problems": [
        {"q": "1 + 1 = ?", "a": 2},
        {"q": "2 + 1 = ?", "a": 3},
        {"q": "1 + 2 = ?", "a": 3},
        {"q": "2 + 2 = ?", "a": 4}
      ]
    },
    {
      "set": 1,
      "problems": [
        {"q": "3 + 1 = ?", "a": 4},
        {"q": "2 + 3 = ?", "a": 5},
        {"q": "4 + 1 = ?", "a": 5},
        {"q": "3 + 2 = ?", "a": 5}
      ]
    },
    {
      "set": 2,
      "problems": [
        {"q": "4 + 2 = ?", "a": 6},
        {"q": "3 + 3 = ?", "a": 6},
        {"q": "5 + 1 = ?", "a": 6},
        {"q": "4 + 3 = ?", "a": 7}
      ]
    },
    {
      "set": 3,
      "problems": [
        {"q": "5 + 2 = ?", "a": 7},
        {"q": "3 + 4 = ?", "a": 7},
        {"q": "5 + 3 = ?", "a": 8},
        {"q": "4 + 4 = ?", "a": 8}
      ]
    },
    {
      "set": 4,
      "problems": [
        {"q": "6 + 2 = ?", "a": 8},
        {"q": "5 + 4 = ?", "a": 9},
        {"q": "6 + 3 = ?", "a": 9},
        {"q": "5 + 5 = ?", "a": 10}
      ]
    }
  ],
  "poppy_age_7": [
    {
      "set": 0,
      "problems": [
        {"q": "3 x 2 = ?", "a": 6},
        {"q": "4 x 2 = ?", "a": 8},
        {"q": "6 / 2 = ?", "a": 3},
        {"q": "5 x 2 = ?", "a": 10}
      ]
    },
    {
      "set": 1,
      "problems": [
        {"q": "3 x 3 = ?", "a": 9},
        {"q": "4 x 3 = ?", "a": 12},
        {"q": "9 / 3 = ?", "a": 3},
        {"q": "5 x 3 = ?", "a": 15}
      ]
    },
    {
      "set": 2,
      "problems": [
        {"q": "4 x 4 = ?", "a": 16},
        {"q": "3 x 5 = ?", "a": 15},
        {"q": "12 / 4 = ?", "a": 3},
        {"q": "6 x 2 = ?", "a": 12}
      ]
    },
    {
      "set": 3,
      "problems": [
        {"q": "5 x 4 = ?", "a": 20},
        {"q": "6 x 3 = ?", "a": 18},
        {"q": "15 / 5 = ?", "a": 3},
        {"q": "4 x 5 = ?", "a": 20}
      ]
    },
    {
      "set": 4,
      "problems": [
        {"q": "6 x 4 = ?", "a": 24},
        {"q": "7 x 3 = ?", "a": 21},
        {"q": "20 / 4 = ?", "a": 5},
        {"q": "5 x 5 = ?", "a": 25}
      ]
    }
  ]
}
